bio_check/_VERSION
bio_check/__init__.py
bio_check/processing_tools.py
bio_check/tests.py
bio_check/verifier.py
bio_check-1.4.0.dist-info/LICENSE
bio_check-1.4.0.dist-info/METADATA
bio_check-1.4.0.dist-info/WHEEL
bio_check-1.4.0.dist-info/RECORD
