Metadata-Version: 2.1
Name: bio-check
Version: 1.4.0
Summary: Simulation Verification Service and API
Author: Alex Patrie
Author-email: alexanderpatrie@gmail.com
Requires-Python: >=3.9
Classifier: Programming Language :: Python :: 3
Classifier: Programming Language :: Python :: 3.9
Classifier: Programming Language :: Python :: 3.10
Classifier: Programming Language :: Python :: 3.11
Classifier: Programming Language :: Python :: 3.12
Provides-Extra: dev
Requires-Dist: biosimulators-tellurium (>=0.1.42,<0.2.0)
Requires-Dist: requests-toolbelt (>=1.0.0,<2.0.0)
Requires-Dist: seaborn (>=0.13.2,<0.14.0)
